LICENSE
README.md
setup.py
includes/__init__.py
includes/const.py
includes/credential.py
includes/helps.py
openredirect7.egg-info/PKG-INFO
openredirect7.egg-info/SOURCES.txt
openredirect7.egg-info/dependency_links.txt
openredirect7.egg-info/requires.txt
openredirect7.egg-info/top_level.txt
utils/__init__.py
utils/check_internet.py
utils/check_redirect.py
utils/url_processor.py