Metadata-Version: 2.1
Name: openredirect7
Version: 1.1.1
Summary: A Tool to find an Easy Bounty - Open Redirect
Home-page: UNKNOWN
Author: @yashwanth
Author-email: yashwanthrvy7@gmail.com
License: UNKNOWN
Platform: UNKNOWN
Classifier: Development Status :: 1 - Planning
Classifier: Intended Audience :: Developers
Classifier: Programming Language :: Python :: 3
Classifier: Operating System :: Unix
Classifier: Operating System :: MacOS :: MacOS X
Classifier: Operating System :: Microsoft :: Windows
License-File: LICENSE
